{
  "source": "NEET data, Population & Housing Census 2022 (BBS) — youth not in education, employment, or training",
  "category_key": "neet_youth",
  "category_label": "NEET & youth (not in education/employment/training)",
  "note": "All values are percentages. District keys match master_data.json names except \"Barishal\" (this file) = \"Barisal\" (master_data), handled at runtime.",
  "metrics": {
    "NEET_Overall_15_24": "NEET Overall (15-24) (%)",
    "NEET_male_Overall_15_24": "NEET male Overall (15-24) (%)",
    "NEET_female_Overall_15_24": "NEET female Overall (15-24) (%)",
    "NEET_rural_Overall_15_24": "NEET rural Overall (15-24) (%)",
    "NEET_male_rural_Overall_15_24": "NEET male rural Overall (15-24) (%)",
    "NEET_female_rural_Overall_15_24": "NEET female rural Overall (15-24) (%)",
    "NEET_urban_Overall_15_24": "NEET urban Overall (15-24) (%)",
    "NEET_male_urban_Overall_15_24": "NEET male urban Overall (15-24) (%)",
    "NEET_female_urban_Overall_15_24": "NEET female urban Overall (15-24) (%)",
    "NEET_15_19_year_overall": "NEET 15 19 year overall (%)",
    "NEET_male_15_19_year": "NEET male 15 19 year (%)",
    "NEET_female_15_19_year": "NEET female 15 19 year (%)",
    "NEET_rural_15_19_year": "NEET rural 15 19 year (%)",
    "NEET_male_rural_15_19_year": "NEET male rural 15 19 year (%)",
    "NEET_female_rural_15_19_year": "NEET female rural 15 19 year (%)",
    "NEET_urban_15_19_year": "NEET urban 15 19 year (%)",
    "NEET_male_urban_15_19_year": "NEET male urban 15 19 year (%)",
    "NEET_female_urban_15_19_year": "NEET female urban 15 19 year (%)",
    "NEET_20_24_year_overall": "NEET 20 24 year overall (%)",
    "NEET_male_20_24_year": "NEET male 20 24 year (%)",
    "NEET_female_20_24_year": "NEET female 20 24 year (%)",
    "NEET_rural_20_24_year": "NEET rural 20 24 year (%)",
    "NEET_male_rural_20_24_year": "NEET male rural 20 24 year (%)",
    "NEET_female_rural_20_24_year": "NEET female rural 20 24 year (%)",
    "NEET_urban_20_24_year": "NEET urban 20 24 year (%)",
    "NEET_male_urban_20_24_year": "NEET male urban 20 24 year (%)",
    "NEET_female_urban_20_24_year": "NEET female urban 20 24 year (%)"
  },
  "by_district": {
    "Bagerhat": {
      "NEET_Overall_15_24": 35.66,
      "NEET_male_Overall_15_24": 13.89,
      "NEET_female_Overall_15_24": 55.29,
      "NEET_rural_Overall_15_24": 35.77,
      "NEET_male_rural_Overall_15_24": 13.92,
      "NEET_female_rural_Overall_15_24": 55.8,
      "NEET_urban_Overall_15_24": 35.32,
      "NEET_male_urban_Overall_15_24": 13.78,
      "NEET_female_urban_Overall_15_24": 53.79,
      "NEET_15_19_year_overall": 27.01,
      "NEET_male_15_19_year": 14.85,
      "NEET_female_15_19_year": 38.71,
      "NEET_rural_15_19_year": 27,
      "NEET_male_rural_15_19_year": 14.74,
      "NEET_female_rural_15_19_year": 38.98,
      "NEET_urban_15_19_year": 27.05,
      "NEET_male_urban_15_19_year": 15.18,
      "NEET_female_urban_15_19_year": 37.92,
      "NEET_20_24_year_overall": 44.95,
      "NEET_male_20_24_year": 12.78,
      "NEET_female_20_24_year": 72.01,
      "NEET_rural_20_24_year": 45.26,
      "NEET_male_rural_20_24_year": 12.97,
      "NEET_female_rural_20_24_year": 72.9,
      "NEET_urban_20_24_year": 44,
      "NEET_male_urban_20_24_year": 12.2,
      "NEET_female_urban_20_24_year": 69.41
    },
    "Bandarban": {
      "NEET_Overall_15_24": 30.44,
      "NEET_male_Overall_15_24": 10.97,
      "NEET_female_Overall_15_24": 49.49,
      "NEET_rural_Overall_15_24": 33.09,
      "NEET_male_rural_Overall_15_24": 12.81,
      "NEET_female_rural_Overall_15_24": 52.17,
      "NEET_urban_Overall_15_24": 26.96,
      "NEET_male_urban_Overall_15_24": 8.67,
      "NEET_female_urban_Overall_15_24": 45.81,
      "NEET_15_19_year_overall": 25.7,
      "NEET_male_15_19_year": 13.53,
      "NEET_female_15_19_year": 37.75,
      "NEET_rural_15_19_year": 29.63,
      "NEET_male_rural_15_19_year": 16.57,
      "NEET_female_rural_15_19_year": 42.16,
      "NEET_urban_15_19_year": 20.67,
      "NEET_male_urban_15_19_year": 9.78,
      "NEET_female_urban_15_19_year": 31.9,
      "NEET_20_24_year_overall": 35.83,
      "NEET_male_20_24_year": 8.02,
      "NEET_female_20_24_year": 62.7,
      "NEET_rural_20_24_year": 36.95,
      "NEET_male_rural_20_24_year": 8.53,
      "NEET_female_rural_20_24_year": 63.14,
      "NEET_urban_20_24_year": 34.33,
      "NEET_male_urban_20_24_year": 7.36,
      "NEET_female_urban_20_24_year": 62.08
    },
    "Barguna": {
      "NEET_Overall_15_24": 35.95,
      "NEET_male_Overall_15_24": 15.71,
      "NEET_female_Overall_15_24": 53.38,
      "NEET_rural_Overall_15_24": 36.96,
      "NEET_male_rural_Overall_15_24": 16.24,
      "NEET_female_rural_Overall_15_24": 55.01,
      "NEET_urban_Overall_15_24": 32.67,
      "NEET_male_urban_Overall_15_24": 13.98,
      "NEET_female_urban_Overall_15_24": 48.22,
      "NEET_15_19_year_overall": 25.44,
      "NEET_male_15_19_year": 15.23,
      "NEET_female_15_19_year": 35.17,
      "NEET_rural_15_19_year": 26.39,
      "NEET_male_rural_15_19_year": 15.83,
      "NEET_female_rural_15_19_year": 36.58,
      "NEET_urban_15_19_year": 22.38,
      "NEET_male_urban_15_19_year": 13.27,
      "NEET_female_urban_15_19_year": 30.73,
      "NEET_20_24_year_overall": 49.01,
      "NEET_male_20_24_year": 16.39,
      "NEET_female_20_24_year": 73.73,
      "NEET_rural_20_24_year": 50.11,
      "NEET_male_rural_20_24_year": 16.81,
      "NEET_female_rural_20_24_year": 75.58,
      "NEET_urban_20_24_year": 45.45,
      "NEET_male_urban_20_24_year": 14.97,
      "NEET_female_urban_20_24_year": 67.88
    },
    "Barishal": {
      "NEET_Overall_15_24": 33.17,
      "NEET_male_Overall_15_24": 14.35,
      "NEET_female_Overall_15_24": 49.36,
      "NEET_rural_Overall_15_24": 35.21,
      "NEET_male_rural_Overall_15_24": 15.59,
      "NEET_female_rural_Overall_15_24": 51.59,
      "NEET_urban_Overall_15_24": 28.87,
      "NEET_male_urban_Overall_15_24": 11.86,
      "NEET_female_urban_Overall_15_24": 44.47,
      "NEET_15_19_year_overall": 23.23,
      "NEET_male_15_19_year": 14.62,
      "NEET_female_15_19_year": 31.36,
      "NEET_rural_15_19_year": 24.42,
      "NEET_male_rural_15_19_year": 15.72,
      "NEET_female_rural_15_19_year": 32.52,
      "NEET_urban_15_19_year": 20.47,
      "NEET_male_urban_15_19_year": 12.13,
      "NEET_female_urban_15_19_year": 28.59,
      "NEET_20_24_year_overall": 44.6,
      "NEET_male_20_24_year": 14,
      "NEET_female_20_24_year": 68.23,
      "NEET_rural_20_24_year": 48.44,
      "NEET_male_rural_20_24_year": 15.4,
      "NEET_female_rural_20_24_year": 72.5,
      "NEET_urban_20_24_year": 37.32,
      "NEET_male_urban_20_24_year": 11.57,
      "NEET_female_urban_20_24_year": 59.51
    },
    "Bhola": {
      "NEET_Overall_15_24": 39.61,
      "NEET_male_Overall_15_24": 12.53,
      "NEET_female_Overall_15_24": 61.35,
      "NEET_rural_Overall_15_24": 40.87,
      "NEET_male_rural_Overall_15_24": 13.11,
      "NEET_female_rural_Overall_15_24": 62.89,
      "NEET_urban_Overall_15_24": 36.36,
      "NEET_male_urban_Overall_15_24": 11.06,
      "NEET_female_urban_Overall_15_24": 57.29,
      "NEET_15_19_year_overall": 29.14,
      "NEET_male_15_19_year": 13.9,
      "NEET_female_15_19_year": 43.08,
      "NEET_rural_15_19_year": 30.51,
      "NEET_male_rural_15_19_year": 14.74,
      "NEET_female_rural_15_19_year": 44.75,
      "NEET_urban_15_19_year": 25.59,
      "NEET_male_urban_15_19_year": 11.81,
      "NEET_female_urban_15_19_year": 38.66,
      "NEET_20_24_year_overall": 51.9,
      "NEET_male_20_24_year": 10.64,
      "NEET_female_20_24_year": 80.24,
      "NEET_rural_20_24_year": 53.05,
      "NEET_male_rural_20_24_year": 10.88,
      "NEET_female_rural_20_24_year": 81.76,
      "NEET_urban_20_24_year": 48.94,
      "NEET_male_urban_20_24_year": 10.03,
      "NEET_female_urban_20_24_year": 76.3
    },
    "Bogura": {
      "NEET_Overall_15_24": 34.13,
      "NEET_male_Overall_15_24": 11.43,
      "NEET_female_Overall_15_24": 55.32,
      "NEET_rural_Overall_15_24": 36.49,
      "NEET_male_rural_Overall_15_24": 12.48,
      "NEET_female_rural_Overall_15_24": 58.32,
      "NEET_urban_Overall_15_24": 28.14,
      "NEET_male_urban_Overall_15_24": 8.85,
      "NEET_female_urban_Overall_15_24": 47.33,
      "NEET_15_19_year_overall": 26.06,
      "NEET_male_15_19_year": 11.22,
      "NEET_female_15_19_year": 41,
      "NEET_rural_15_19_year": 28.07,
      "NEET_male_rural_15_19_year": 12.25,
      "NEET_female_rural_15_19_year": 43.7,
      "NEET_urban_15_19_year": 20.8,
      "NEET_male_urban_15_19_year": 8.63,
      "NEET_female_urban_15_19_year": 33.68,
      "NEET_20_24_year_overall": 43.46,
      "NEET_male_20_24_year": 11.68,
      "NEET_female_20_24_year": 70.62,
      "NEET_rural_20_24_year": 46.37,
      "NEET_male_rural_20_24_year": 12.79,
      "NEET_female_rural_20_24_year": 74.12,
      "NEET_urban_20_24_year": 36.27,
      "NEET_male_urban_20_24_year": 9.1,
      "NEET_female_urban_20_24_year": 61.49
    },
    "Brahmanbaria": {
      "NEET_Overall_15_24": 41.7,
      "NEET_male_Overall_15_24": 20.19,
      "NEET_female_Overall_15_24": 57.32,
      "NEET_rural_Overall_15_24": 43.33,
      "NEET_male_rural_Overall_15_24": 21.75,
      "NEET_female_rural_Overall_15_24": 58.61,
      "NEET_urban_Overall_15_24": 35.68,
      "NEET_male_urban_Overall_15_24": 14.79,
      "NEET_female_urban_Overall_15_24": 52.34,
      "NEET_15_19_year_overall": 31.64,
      "NEET_male_15_19_year": 21.21,
      "NEET_female_15_19_year": 40.03,
      "NEET_rural_15_19_year": 33.23,
      "NEET_male_rural_15_19_year": 22.99,
      "NEET_female_rural_15_19_year": 41.25,
      "NEET_urban_15_19_year": 25.76,
      "NEET_male_urban_15_19_year": 15.04,
      "NEET_female_urban_15_19_year": 35.26,
      "NEET_20_24_year_overall": 54.59,
      "NEET_male_20_24_year": 18.68,
      "NEET_female_20_24_year": 77.44,
      "NEET_rural_20_24_year": 56.34,
      "NEET_male_rural_20_24_year": 19.93,
      "NEET_female_rural_20_24_year": 78.92,
      "NEET_urban_20_24_year": 48.22,
      "NEET_male_urban_20_24_year": 14.44,
      "NEET_female_urban_20_24_year": 71.78
    },
    "Chandpur": {
      "NEET_Overall_15_24": 40.32,
      "NEET_male_Overall_15_24": 18.65,
      "NEET_female_Overall_15_24": 56.44,
      "NEET_rural_Overall_15_24": 41.35,
      "NEET_male_rural_Overall_15_24": 19.39,
      "NEET_female_rural_Overall_15_24": 57.34,
      "NEET_urban_Overall_15_24": 37.43,
      "NEET_male_urban_Overall_15_24": 16.68,
      "NEET_female_urban_Overall_15_24": 53.83,
      "NEET_15_19_year_overall": 27.84,
      "NEET_male_15_19_year": 18.6,
      "NEET_female_15_19_year": 35.58,
      "NEET_rural_15_19_year": 28.61,
      "NEET_male_rural_15_19_year": 19.38,
      "NEET_female_rural_15_19_year": 36.18,
      "NEET_urban_15_19_year": 25.67,
      "NEET_male_urban_15_19_year": 16.46,
      "NEET_female_urban_15_19_year": 33.82,
      "NEET_20_24_year_overall": 55.02,
      "NEET_male_20_24_year": 18.72,
      "NEET_female_20_24_year": 78.48,
      "NEET_rural_20_24_year": 56.48,
      "NEET_male_rural_20_24_year": 19.39,
      "NEET_female_rural_20_24_year": 79.85,
      "NEET_urban_20_24_year": 50.97,
      "NEET_male_urban_20_24_year": 16.98,
      "NEET_female_urban_20_24_year": 74.54
    },
    "Chapainawabganj": {
      "NEET_Overall_15_24": 38.47,
      "NEET_male_Overall_15_24": 11.24,
      "NEET_female_Overall_15_24": 61.3,
      "NEET_rural_Overall_15_24": 39.54,
      "NEET_male_rural_Overall_15_24": 11.35,
      "NEET_female_rural_Overall_15_24": 63.26,
      "NEET_urban_Overall_15_24": 35.46,
      "NEET_male_urban_Overall_15_24": 10.93,
      "NEET_female_urban_Overall_15_24": 55.83,
      "NEET_15_19_year_overall": 31.38,
      "NEET_male_15_19_year": 12.08,
      "NEET_female_15_19_year": 48.51,
      "NEET_rural_15_19_year": 32.9,
      "NEET_male_rural_15_19_year": 12.71,
      "NEET_female_rural_15_19_year": 50.82,
      "NEET_urban_15_19_year": 27.05,
      "NEET_male_urban_15_19_year": 10.27,
      "NEET_female_urban_15_19_year": 41.94,
      "NEET_20_24_year_overall": 46.42,
      "NEET_male_20_24_year": 10.25,
      "NEET_female_20_24_year": 74.86,
      "NEET_rural_20_24_year": 47.01,
      "NEET_male_rural_20_24_year": 9.72,
      "NEET_female_rural_20_24_year": 76.52,
      "NEET_urban_20_24_year": 44.74,
      "NEET_male_urban_20_24_year": 11.72,
      "NEET_female_urban_20_24_year": 70.27
    },
    "Chattogram": {
      "NEET_Overall_15_24": 30.38,
      "NEET_male_Overall_15_24": 12.16,
      "NEET_female_Overall_15_24": 46.62,
      "NEET_rural_Overall_15_24": 34,
      "NEET_male_rural_Overall_15_24": 13.4,
      "NEET_female_rural_Overall_15_24": 52.25,
      "NEET_urban_Overall_15_24": 27.39,
      "NEET_male_urban_Overall_15_24": 11.13,
      "NEET_female_urban_Overall_15_24": 41.92,
      "NEET_15_19_year_overall": 21.96,
      "NEET_male_15_19_year": 13.42,
      "NEET_female_15_19_year": 30.05,
      "NEET_rural_15_19_year": 23.58,
      "NEET_male_rural_15_19_year": 14.37,
      "NEET_female_rural_15_19_year": 32.42,
      "NEET_urban_15_19_year": 20.49,
      "NEET_male_urban_15_19_year": 12.56,
      "NEET_female_urban_15_19_year": 27.93,
      "NEET_20_24_year_overall": 39.23,
      "NEET_male_20_24_year": 10.74,
      "NEET_female_20_24_year": 62.99,
      "NEET_rural_20_24_year": 46.08,
      "NEET_male_rural_20_24_year": 12.18,
      "NEET_female_rural_20_24_year": 73.47,
      "NEET_urban_20_24_year": 34.06,
      "NEET_male_urban_20_24_year": 9.68,
      "NEET_female_urban_20_24_year": 54.87
    },
    "Chuadanga": {
      "NEET_Overall_15_24": 36.67,
      "NEET_male_Overall_15_24": 10.28,
      "NEET_female_Overall_15_24": 60.52,
      "NEET_rural_Overall_15_24": 37.36,
      "NEET_male_rural_Overall_15_24": 10.23,
      "NEET_female_rural_Overall_15_24": 62.19,
      "NEET_urban_Overall_15_24": 34.58,
      "NEET_male_urban_Overall_15_24": 10.43,
      "NEET_female_urban_Overall_15_24": 55.57,
      "NEET_15_19_year_overall": 28.7,
      "NEET_male_15_19_year": 11.58,
      "NEET_female_15_19_year": 44.99,
      "NEET_rural_15_19_year": 29.56,
      "NEET_male_rural_15_19_year": 11.67,
      "NEET_female_rural_15_19_year": 46.76,
      "NEET_urban_15_19_year": 26,
      "NEET_male_urban_15_19_year": 11.28,
      "NEET_female_urban_15_19_year": 39.61,
      "NEET_20_24_year_overall": 45.61,
      "NEET_male_20_24_year": 8.74,
      "NEET_female_20_24_year": 77.03,
      "NEET_rural_20_24_year": 46.18,
      "NEET_male_rural_20_24_year": 8.51,
      "NEET_female_rural_20_24_year": 78.79,
      "NEET_urban_20_24_year": 43.9,
      "NEET_male_urban_20_24_year": 9.44,
      "NEET_female_urban_20_24_year": 71.93
    },
    "Cox's Bazar": {
      "NEET_Overall_15_24": 35.76,
      "NEET_male_Overall_15_24": 13.22,
      "NEET_female_Overall_15_24": 57.1,
      "NEET_rural_Overall_15_24": 36.74,
      "NEET_male_rural_Overall_15_24": 13.81,
      "NEET_female_rural_Overall_15_24": 57.98,
      "NEET_urban_Overall_15_24": 34.5,
      "NEET_male_urban_Overall_15_24": 12.49,
      "NEET_female_urban_Overall_15_24": 55.95,
      "NEET_15_19_year_overall": 28.94,
      "NEET_male_15_19_year": 15.57,
      "NEET_female_15_19_year": 42.03,
      "NEET_rural_15_19_year": 29.76,
      "NEET_male_rural_15_19_year": 16.3,
      "NEET_female_rural_15_19_year": 42.83,
      "NEET_urban_15_19_year": 27.86,
      "NEET_male_urban_15_19_year": 14.61,
      "NEET_female_urban_15_19_year": 40.97,
      "NEET_20_24_year_overall": 43.98,
      "NEET_male_20_24_year": 10.28,
      "NEET_female_20_24_year": 74.65,
      "NEET_rural_20_24_year": 45.52,
      "NEET_male_rural_20_24_year": 10.51,
      "NEET_female_rural_20_24_year": 76.07,
      "NEET_urban_20_24_year": 42.12,
      "NEET_male_urban_20_24_year": 10.01,
      "NEET_female_urban_20_24_year": 72.85
    },
    "Cumilla": {
      "NEET_Overall_15_24": 39.01,
      "NEET_male_Overall_15_24": 17.03,
      "NEET_female_Overall_15_24": 55.52,
      "NEET_rural_Overall_15_24": 40.47,
      "NEET_male_rural_Overall_15_24": 17.94,
      "NEET_female_rural_Overall_15_24": 56.88,
      "NEET_urban_Overall_15_24": 33.55,
      "NEET_male_urban_Overall_15_24": 13.92,
      "NEET_female_urban_Overall_15_24": 50.11,
      "NEET_15_19_year_overall": 27.31,
      "NEET_male_15_19_year": 17.22,
      "NEET_female_15_19_year": 35.89,
      "NEET_rural_15_19_year": 28.29,
      "NEET_male_rural_15_19_year": 18.08,
      "NEET_female_rural_15_19_year": 36.77,
      "NEET_urban_15_19_year": 23.57,
      "NEET_male_urban_15_19_year": 14.08,
      "NEET_female_urban_15_19_year": 32.32,
      "NEET_20_24_year_overall": 53.02,
      "NEET_male_20_24_year": 16.77,
      "NEET_female_20_24_year": 76.46,
      "NEET_rural_20_24_year": 55.28,
      "NEET_male_rural_20_24_year": 17.73,
      "NEET_female_rural_20_24_year": 78.45,
      "NEET_urban_20_24_year": 44.88,
      "NEET_male_urban_20_24_year": 13.72,
      "NEET_female_urban_20_24_year": 68.65
    },
    "Dhaka": {
      "NEET_Overall_15_24": 25.44,
      "NEET_male_Overall_15_24": 8.89,
      "NEET_female_Overall_15_24": 42.49,
      "NEET_rural_Overall_15_24": 28.64,
      "NEET_male_rural_Overall_15_24": 10.02,
      "NEET_female_rural_Overall_15_24": 45.06,
      "NEET_urban_Overall_15_24": 24.44,
      "NEET_male_urban_Overall_15_24": 8.57,
      "NEET_female_urban_Overall_15_24": 41.6,
      "NEET_15_19_year_overall": 21.13,
      "NEET_male_15_19_year": 10.21,
      "NEET_female_15_19_year": 32.65,
      "NEET_rural_15_19_year": 24.77,
      "NEET_male_rural_15_19_year": 12.28,
      "NEET_female_rural_15_19_year": 36.23,
      "NEET_urban_15_19_year": 19.97,
      "NEET_male_urban_15_19_year": 9.62,
      "NEET_female_urban_15_19_year": 31.4,
      "NEET_20_24_year_overall": 29.06,
      "NEET_male_20_24_year": 7.75,
      "NEET_female_20_24_year": 50.57,
      "NEET_rural_20_24_year": 31.91,
      "NEET_male_rural_20_24_year": 8.02,
      "NEET_female_rural_20_24_year": 52.3,
      "NEET_urban_20_24_year": 28.16,
      "NEET_male_urban_20_24_year": 7.67,
      "NEET_female_urban_20_24_year": 49.96
    },
    "Dinajpur": {
      "NEET_Overall_15_24": 32.44,
      "NEET_male_Overall_15_24": 10.82,
      "NEET_female_Overall_15_24": 52.46,
      "NEET_rural_Overall_15_24": 34.2,
      "NEET_male_rural_Overall_15_24": 11.41,
      "NEET_female_rural_Overall_15_24": 55.03,
      "NEET_urban_Overall_15_24": 25.66,
      "NEET_male_urban_Overall_15_24": 8.6,
      "NEET_female_urban_Overall_15_24": 42.25,
      "NEET_15_19_year_overall": 23.8,
      "NEET_male_15_19_year": 10.55,
      "NEET_female_15_19_year": 36.77,
      "NEET_rural_15_19_year": 25.27,
      "NEET_male_rural_15_19_year": 11.17,
      "NEET_female_rural_15_19_year": 38.85,
      "NEET_urban_15_19_year": 18,
      "NEET_male_urban_15_19_year": 8.22,
      "NEET_female_urban_15_19_year": 28.22,
      "NEET_20_24_year_overall": 42.55,
      "NEET_male_20_24_year": 11.16,
      "NEET_female_20_24_year": 69.79,
      "NEET_rural_20_24_year": 44.73,
      "NEET_male_rural_20_24_year": 11.72,
      "NEET_female_rural_20_24_year": 73.13,
      "NEET_urban_20_24_year": 34.33,
      "NEET_male_urban_20_24_year": 9.06,
      "NEET_female_urban_20_24_year": 56.95
    },
    "Faridpur": {
      "NEET_Overall_15_24": 38.03,
      "NEET_male_Overall_15_24": 15.04,
      "NEET_female_Overall_15_24": 57.1,
      "NEET_rural_Overall_15_24": 40.22,
      "NEET_male_rural_Overall_15_24": 16.16,
      "NEET_female_rural_Overall_15_24": 59.88,
      "NEET_urban_Overall_15_24": 31.49,
      "NEET_male_urban_Overall_15_24": 11.8,
      "NEET_female_urban_Overall_15_24": 48.55,
      "NEET_15_19_year_overall": 28.93,
      "NEET_male_15_19_year": 16.35,
      "NEET_female_15_19_year": 40.34,
      "NEET_rural_15_19_year": 30.89,
      "NEET_male_rural_15_19_year": 17.79,
      "NEET_female_rural_15_19_year": 42.57,
      "NEET_urban_15_19_year": 22.91,
      "NEET_male_urban_15_19_year": 12.08,
      "NEET_female_urban_15_19_year": 33.29,
      "NEET_20_24_year_overall": 48.26,
      "NEET_male_20_24_year": 13.41,
      "NEET_female_20_24_year": 74.36,
      "NEET_rural_20_24_year": 50.85,
      "NEET_male_rural_20_24_year": 14.1,
      "NEET_female_rural_20_24_year": 78.04,
      "NEET_urban_20_24_year": 40.76,
      "NEET_male_urban_20_24_year": 11.45,
      "NEET_female_urban_20_24_year": 63.48
    },
    "Feni": {
      "NEET_Overall_15_24": 36.92,
      "NEET_male_Overall_15_24": 15.55,
      "NEET_female_Overall_15_24": 55.05,
      "NEET_rural_Overall_15_24": 39.26,
      "NEET_male_rural_Overall_15_24": 17.17,
      "NEET_female_rural_Overall_15_24": 56.86,
      "NEET_urban_Overall_15_24": 31.72,
      "NEET_male_urban_Overall_15_24": 12.3,
      "NEET_female_urban_Overall_15_24": 50.62,
      "NEET_15_19_year_overall": 24.21,
      "NEET_male_15_19_year": 14.4,
      "NEET_female_15_19_year": 33.68,
      "NEET_rural_15_19_year": 25.82,
      "NEET_male_rural_15_19_year": 15.92,
      "NEET_female_rural_15_19_year": 34.78,
      "NEET_urban_15_19_year": 20.68,
      "NEET_male_urban_15_19_year": 11.41,
      "NEET_female_urban_15_19_year": 31.01,
      "NEET_20_24_year_overall": 52.12,
      "NEET_male_20_24_year": 17.15,
      "NEET_female_20_24_year": 77.46,
      "NEET_rural_20_24_year": 55.1,
      "NEET_male_rural_20_24_year": 18.88,
      "NEET_female_rural_20_24_year": 79.89,
      "NEET_urban_20_24_year": 45.33,
      "NEET_male_urban_20_24_year": 13.58,
      "NEET_female_urban_20_24_year": 71.45
    },
    "Gaibandha": {
      "NEET_Overall_15_24": 35.4,
      "NEET_male_Overall_15_24": 13.14,
      "NEET_female_Overall_15_24": 54.19,
      "NEET_rural_Overall_15_24": 36.24,
      "NEET_male_rural_Overall_15_24": 13.38,
      "NEET_female_rural_Overall_15_24": 55.47,
      "NEET_urban_Overall_15_24": 31.07,
      "NEET_male_urban_Overall_15_24": 11.89,
      "NEET_female_urban_Overall_15_24": 47.48,
      "NEET_15_19_year_overall": 25.34,
      "NEET_male_15_19_year": 12.79,
      "NEET_female_15_19_year": 37.42,
      "NEET_rural_15_19_year": 26.08,
      "NEET_male_rural_15_19_year": 13.07,
      "NEET_female_rural_15_19_year": 38.6,
      "NEET_urban_15_19_year": 21.54,
      "NEET_male_urban_15_19_year": 11.35,
      "NEET_female_urban_15_19_year": 31.36,
      "NEET_20_24_year_overall": 48.31,
      "NEET_male_20_24_year": 13.68,
      "NEET_female_20_24_year": 72.94,
      "NEET_rural_20_24_year": 49.19,
      "NEET_male_rural_20_24_year": 13.87,
      "NEET_female_rural_20_24_year": 74.2,
      "NEET_urban_20_24_year": 43.62,
      "NEET_male_urban_20_24_year": 12.71,
      "NEET_female_urban_20_24_year": 66.18
    },
    "Gazipur": {
      "NEET_Overall_15_24": 26.37,
      "NEET_male_Overall_15_24": 9.55,
      "NEET_female_Overall_15_24": 40.73,
      "NEET_rural_Overall_15_24": 29.47,
      "NEET_male_rural_Overall_15_24": 10.96,
      "NEET_female_rural_Overall_15_24": 45.21,
      "NEET_urban_Overall_15_24": 24.87,
      "NEET_male_urban_Overall_15_24": 8.87,
      "NEET_female_urban_Overall_15_24": 38.56,
      "NEET_15_19_year_overall": 23.21,
      "NEET_male_15_19_year": 12.1,
      "NEET_female_15_19_year": 32.68,
      "NEET_rural_15_19_year": 24.02,
      "NEET_male_rural_15_19_year": 12.69,
      "NEET_female_rural_15_19_year": 33.92,
      "NEET_urban_15_19_year": 22.78,
      "NEET_male_urban_15_19_year": 11.77,
      "NEET_female_urban_15_19_year": 32.02,
      "NEET_20_24_year_overall": 28.92,
      "NEET_male_20_24_year": 7.5,
      "NEET_female_20_24_year": 47.23,
      "NEET_rural_20_24_year": 34.54,
      "NEET_male_rural_20_24_year": 9.29,
      "NEET_female_rural_20_24_year": 55.43,
      "NEET_urban_20_24_year": 26.45,
      "NEET_male_urban_20_24_year": 6.73,
      "NEET_female_urban_20_24_year": 43.54
    },
    "Gopalganj": {
      "NEET_Overall_15_24": 32.82,
      "NEET_male_Overall_15_24": 12.74,
      "NEET_female_Overall_15_24": 51.32,
      "NEET_rural_Overall_15_24": 34.61,
      "NEET_male_rural_Overall_15_24": 13.63,
      "NEET_female_rural_Overall_15_24": 53.67,
      "NEET_urban_Overall_15_24": 26.56,
      "NEET_male_urban_Overall_15_24": 9.76,
      "NEET_female_urban_Overall_15_24": 42.83,
      "NEET_15_19_year_overall": 24.54,
      "NEET_male_15_19_year": 13.32,
      "NEET_female_15_19_year": 35.76,
      "NEET_rural_15_19_year": 25.49,
      "NEET_male_rural_15_19_year": 13.92,
      "NEET_female_rural_15_19_year": 37.1,
      "NEET_urban_15_19_year": 20.72,
      "NEET_male_urban_15_19_year": 10.89,
      "NEET_female_urban_15_19_year": 30.42,
      "NEET_20_24_year_overall": 42.58,
      "NEET_male_20_24_year": 11.99,
      "NEET_female_20_24_year": 68.15,
      "NEET_rural_20_24_year": 46.09,
      "NEET_male_rural_20_24_year": 13.21,
      "NEET_female_rural_20_24_year": 72.42,
      "NEET_urban_20_24_year": 32.04,
      "NEET_male_urban_20_24_year": 8.68,
      "NEET_female_urban_20_24_year": 54.28
    },
    "Habiganj": {
      "NEET_Overall_15_24": 39.14,
      "NEET_male_Overall_15_24": 18.53,
      "NEET_female_Overall_15_24": 56.4,
      "NEET_rural_Overall_15_24": 40.03,
      "NEET_male_rural_Overall_15_24": 19.09,
      "NEET_female_rural_Overall_15_24": 57.53,
      "NEET_urban_Overall_15_24": 34.1,
      "NEET_male_urban_Overall_15_24": 15.33,
      "NEET_female_urban_Overall_15_24": 49.94,
      "NEET_15_19_year_overall": 32.64,
      "NEET_male_15_19_year": 21.56,
      "NEET_female_15_19_year": 42.5,
      "NEET_rural_15_19_year": 33.71,
      "NEET_male_rural_15_19_year": 22.45,
      "NEET_female_rural_15_19_year": 43.7,
      "NEET_urban_15_19_year": 26.48,
      "NEET_male_urban_15_19_year": 16.52,
      "NEET_female_urban_15_19_year": 35.49,
      "NEET_20_24_year_overall": 46.94,
      "NEET_male_20_24_year": 14.61,
      "NEET_female_20_24_year": 72.1,
      "NEET_rural_20_24_year": 47.65,
      "NEET_male_rural_20_24_year": 14.75,
      "NEET_female_rural_20_24_year": 73.25,
      "NEET_urban_20_24_year": 42.97,
      "NEET_male_urban_20_24_year": 13.83,
      "NEET_female_urban_20_24_year": 65.69
    },
    "Jamalpur": {
      "NEET_Overall_15_24": 34.73,
      "NEET_male_Overall_15_24": 14.06,
      "NEET_female_Overall_15_24": 52.42,
      "NEET_rural_Overall_15_24": 35.36,
      "NEET_male_rural_Overall_15_24": 14.44,
      "NEET_female_rural_Overall_15_24": 53.37,
      "NEET_urban_Overall_15_24": 33.04,
      "NEET_male_urban_Overall_15_24": 13.02,
      "NEET_female_urban_Overall_15_24": 49.91,
      "NEET_15_19_year_overall": 24.84,
      "NEET_male_15_19_year": 13.77,
      "NEET_female_15_19_year": 35.63,
      "NEET_rural_15_19_year": 25.28,
      "NEET_male_rural_15_19_year": 14.13,
      "NEET_female_rural_15_19_year": 36.3,
      "NEET_urban_15_19_year": 23.65,
      "NEET_male_urban_15_19_year": 12.79,
      "NEET_female_urban_15_19_year": 33.86,
      "NEET_20_24_year_overall": 47.52,
      "NEET_male_20_24_year": 14.48,
      "NEET_female_20_24_year": 71.35,
      "NEET_rural_20_24_year": 48.53,
      "NEET_male_rural_20_24_year": 14.92,
      "NEET_female_rural_20_24_year": 72.63,
      "NEET_urban_20_24_year": 44.86,
      "NEET_male_urban_20_24_year": 13.35,
      "NEET_female_urban_20_24_year": 67.94
    },
    "Jashore": {
      "NEET_Overall_15_24": 35.21,
      "NEET_male_Overall_15_24": 10.97,
      "NEET_female_Overall_15_24": 57.38,
      "NEET_rural_Overall_15_24": 36.75,
      "NEET_male_rural_Overall_15_24": 11.58,
      "NEET_female_rural_Overall_15_24": 59.41,
      "NEET_urban_Overall_15_24": 30.54,
      "NEET_male_urban_Overall_15_24": 9.18,
      "NEET_female_urban_Overall_15_24": 50.99,
      "NEET_15_19_year_overall": 27.21,
      "NEET_male_15_19_year": 11.96,
      "NEET_female_15_19_year": 41.89,
      "NEET_rural_15_19_year": 28.42,
      "NEET_male_rural_15_19_year": 12.55,
      "NEET_female_rural_15_19_year": 43.57,
      "NEET_urban_15_19_year": 23.29,
      "NEET_male_urban_15_19_year": 10.08,
      "NEET_female_urban_15_19_year": 36.38,
      "NEET_20_24_year_overall": 43.79,
      "NEET_male_20_24_year": 9.85,
      "NEET_female_20_24_year": 73.15,
      "NEET_rural_20_24_year": 45.93,
      "NEET_male_rural_20_24_year": 10.43,
      "NEET_female_rural_20_24_year": 75.93,
      "NEET_urban_20_24_year": 37.64,
      "NEET_male_urban_20_24_year": 8.28,
      "NEET_female_urban_20_24_year": 64.83
    },
    "Jhalokati": {
      "NEET_Overall_15_24": 33.19,
      "NEET_male_Overall_15_24": 14.73,
      "NEET_female_Overall_15_24": 48.41,
      "NEET_rural_Overall_15_24": 34.22,
      "NEET_male_rural_Overall_15_24": 15.37,
      "NEET_female_rural_Overall_15_24": 49.32,
      "NEET_urban_Overall_15_24": 30.61,
      "NEET_male_urban_Overall_15_24": 13.23,
      "NEET_female_urban_Overall_15_24": 46.02,
      "NEET_15_19_year_overall": 21,
      "NEET_male_15_19_year": 13.37,
      "NEET_female_15_19_year": 28.25,
      "NEET_rural_15_19_year": 21.88,
      "NEET_male_rural_15_19_year": 14.21,
      "NEET_female_rural_15_19_year": 28.85,
      "NEET_urban_15_19_year": 18.8,
      "NEET_male_urban_15_19_year": 11.44,
      "NEET_female_urban_15_19_year": 26.62,
      "NEET_20_24_year_overall": 48.51,
      "NEET_male_20_24_year": 16.78,
      "NEET_female_20_24_year": 70.3,
      "NEET_rural_20_24_year": 49.62,
      "NEET_male_rural_20_24_year": 17.06,
      "NEET_female_rural_20_24_year": 71.8,
      "NEET_urban_20_24_year": 45.68,
      "NEET_male_urban_20_24_year": 16.08,
      "NEET_female_urban_20_24_year": 66.45
    },
    "Jhenaidah": {
      "NEET_Overall_15_24": 33.95,
      "NEET_male_Overall_15_24": 10.35,
      "NEET_female_Overall_15_24": 55.89,
      "NEET_rural_Overall_15_24": 34.86,
      "NEET_male_rural_Overall_15_24": 10.55,
      "NEET_female_rural_Overall_15_24": 57.53,
      "NEET_urban_Overall_15_24": 30.66,
      "NEET_male_urban_Overall_15_24": 9.64,
      "NEET_female_urban_Overall_15_24": 49.98,
      "NEET_15_19_year_overall": 25.67,
      "NEET_male_15_19_year": 10.84,
      "NEET_female_15_19_year": 40.16,
      "NEET_rural_15_19_year": 26.75,
      "NEET_male_rural_15_19_year": 11.18,
      "NEET_female_rural_15_19_year": 41.9,
      "NEET_urban_15_19_year": 21.84,
      "NEET_male_urban_15_19_year": 9.61,
      "NEET_female_urban_15_19_year": 33.91,
      "NEET_20_24_year_overall": 43.05,
      "NEET_male_20_24_year": 9.8,
      "NEET_female_20_24_year": 72.33,
      "NEET_rural_20_24_year": 43.68,
      "NEET_male_rural_20_24_year": 9.82,
      "NEET_female_rural_20_24_year": 73.82,
      "NEET_urban_20_24_year": 40.68,
      "NEET_male_urban_20_24_year": 9.69,
      "NEET_female_urban_20_24_year": 66.94
    },
    "Joypurhat": {
      "NEET_Overall_15_24": 35.09,
      "NEET_male_Overall_15_24": 13.44,
      "NEET_female_Overall_15_24": 54.47,
      "NEET_rural_Overall_15_24": 37.24,
      "NEET_male_rural_Overall_15_24": 14.47,
      "NEET_female_rural_Overall_15_24": 57.61,
      "NEET_urban_Overall_15_24": 28.55,
      "NEET_male_urban_Overall_15_24": 10.3,
      "NEET_female_urban_Overall_15_24": 44.89,
      "NEET_15_19_year_overall": 25.27,
      "NEET_male_15_19_year": 11.65,
      "NEET_female_15_19_year": 38.09,
      "NEET_rural_15_19_year": 27.19,
      "NEET_male_rural_15_19_year": 12.55,
      "NEET_female_rural_15_19_year": 41.04,
      "NEET_urban_15_19_year": 19.37,
      "NEET_male_urban_15_19_year": 8.84,
      "NEET_female_urban_15_19_year": 29.13,
      "NEET_20_24_year_overall": 46.42,
      "NEET_male_20_24_year": 15.64,
      "NEET_female_20_24_year": 72.42,
      "NEET_rural_20_24_year": 48.84,
      "NEET_male_rural_20_24_year": 16.83,
      "NEET_female_rural_20_24_year": 75.71,
      "NEET_urban_20_24_year": 39.07,
      "NEET_male_urban_20_24_year": 12.06,
      "NEET_female_urban_20_24_year": 62.32
    },
    "Khagrachhari": {
      "NEET_Overall_15_24": 35.31,
      "NEET_male_Overall_15_24": 14.09,
      "NEET_female_Overall_15_24": 54.84,
      "NEET_rural_Overall_15_24": 37.08,
      "NEET_male_rural_Overall_15_24": 15.53,
      "NEET_female_rural_Overall_15_24": 56.91,
      "NEET_urban_Overall_15_24": 32.97,
      "NEET_male_urban_Overall_15_24": 12.19,
      "NEET_female_urban_Overall_15_24": 52.09,
      "NEET_15_19_year_overall": 27.53,
      "NEET_male_15_19_year": 16.04,
      "NEET_female_15_19_year": 38.23,
      "NEET_rural_15_19_year": 29.65,
      "NEET_male_rural_15_19_year": 17.86,
      "NEET_female_rural_15_19_year": 40.69,
      "NEET_urban_15_19_year": 24.76,
      "NEET_male_urban_15_19_year": 13.64,
      "NEET_female_urban_15_19_year": 35.04,
      "NEET_20_24_year_overall": 43.83,
      "NEET_male_20_24_year": 11.93,
      "NEET_female_20_24_year": 72.79,
      "NEET_rural_20_24_year": 45.11,
      "NEET_male_rural_20_24_year": 12.96,
      "NEET_female_rural_20_24_year": 74.14,
      "NEET_urban_20_24_year": 42.1,
      "NEET_male_urban_20_24_year": 10.56,
      "NEET_female_urban_20_24_year": 70.96
    },
    "Khulna": {
      "NEET_Overall_15_24": 31.91,
      "NEET_male_Overall_15_24": 10.73,
      "NEET_female_Overall_15_24": 51.72,
      "NEET_rural_Overall_15_24": 35.09,
      "NEET_male_rural_Overall_15_24": 11.52,
      "NEET_female_rural_Overall_15_24": 56.84,
      "NEET_urban_Overall_15_24": 27.79,
      "NEET_male_urban_Overall_15_24": 9.72,
      "NEET_female_urban_Overall_15_24": 44.99,
      "NEET_15_19_year_overall": 24.53,
      "NEET_male_15_19_year": 11.54,
      "NEET_female_15_19_year": 37.34,
      "NEET_rural_15_19_year": 27.51,
      "NEET_male_rural_15_19_year": 12.67,
      "NEET_female_rural_15_19_year": 41.75,
      "NEET_urban_15_19_year": 20.58,
      "NEET_male_urban_15_19_year": 10.08,
      "NEET_female_urban_15_19_year": 31.3,
      "NEET_20_24_year_overall": 39.12,
      "NEET_male_20_24_year": 9.9,
      "NEET_female_20_24_year": 65.07,
      "NEET_rural_20_24_year": 42.65,
      "NEET_male_rural_20_24_year": 10.34,
      "NEET_female_rural_20_24_year": 71.31,
      "NEET_urban_20_24_year": 34.65,
      "NEET_male_urban_20_24_year": 9.36,
      "NEET_female_urban_20_24_year": 57.17
    },
    "Kishoregonj": {
      "NEET_Overall_15_24": 37.75,
      "NEET_male_Overall_15_24": 17.16,
      "NEET_female_Overall_15_24": 54.77,
      "NEET_rural_Overall_15_24": 39.16,
      "NEET_male_rural_Overall_15_24": 18.25,
      "NEET_female_rural_Overall_15_24": 56.47,
      "NEET_urban_Overall_15_24": 34.18,
      "NEET_male_urban_Overall_15_24": 14.42,
      "NEET_female_urban_Overall_15_24": 50.49,
      "NEET_15_19_year_overall": 29.33,
      "NEET_male_15_19_year": 18.84,
      "NEET_female_15_19_year": 38.78,
      "NEET_rural_15_19_year": 30.77,
      "NEET_male_rural_15_19_year": 20.24,
      "NEET_female_rural_15_19_year": 40.3,
      "NEET_urban_15_19_year": 25.66,
      "NEET_male_urban_15_19_year": 15.29,
      "NEET_female_urban_15_19_year": 34.95,
      "NEET_20_24_year_overall": 48.18,
      "NEET_male_20_24_year": 14.84,
      "NEET_female_20_24_year": 72.9,
      "NEET_rural_20_24_year": 49.61,
      "NEET_male_rural_20_24_year": 15.49,
      "NEET_female_rural_20_24_year": 74.87,
      "NEET_urban_20_24_year": 44.61,
      "NEET_male_urban_20_24_year": 13.24,
      "NEET_female_urban_20_24_year": 67.98
    },
    "Kurigram": {
      "NEET_Overall_15_24": 37.96,
      "NEET_male_Overall_15_24": 14.91,
      "NEET_female_Overall_15_24": 58.35,
      "NEET_rural_Overall_15_24": 39.18,
      "NEET_male_rural_Overall_15_24": 15.66,
      "NEET_female_rural_Overall_15_24": 59.98,
      "NEET_urban_Overall_15_24": 33.77,
      "NEET_male_urban_Overall_15_24": 12.34,
      "NEET_female_urban_Overall_15_24": 52.75,
      "NEET_15_19_year_overall": 28.94,
      "NEET_male_15_19_year": 15.29,
      "NEET_female_15_19_year": 42.45,
      "NEET_rural_15_19_year": 30.25,
      "NEET_male_rural_15_19_year": 16.27,
      "NEET_female_rural_15_19_year": 44.11,
      "NEET_urban_15_19_year": 24.42,
      "NEET_male_urban_15_19_year": 11.89,
      "NEET_female_urban_15_19_year": 36.78,
      "NEET_20_24_year_overall": 48.8,
      "NEET_male_20_24_year": 14.4,
      "NEET_female_20_24_year": 75.37,
      "NEET_rural_20_24_year": 49.92,
      "NEET_male_rural_20_24_year": 14.83,
      "NEET_female_rural_20_24_year": 76.98,
      "NEET_urban_20_24_year": 44.97,
      "NEET_male_urban_20_24_year": 12.94,
      "NEET_female_urban_20_24_year": 69.86
    },
    "Kushtia": {
      "NEET_Overall_15_24": 33.52,
      "NEET_male_Overall_15_24": 10.23,
      "NEET_female_Overall_15_24": 54.53,
      "NEET_rural_Overall_15_24": 34.86,
      "NEET_male_rural_Overall_15_24": 10.44,
      "NEET_female_rural_Overall_15_24": 56.81,
      "NEET_urban_Overall_15_24": 28.88,
      "NEET_male_urban_Overall_15_24": 9.49,
      "NEET_female_urban_Overall_15_24": 46.6,
      "NEET_15_19_year_overall": 24.37,
      "NEET_male_15_19_year": 10.29,
      "NEET_female_15_19_year": 38.21,
      "NEET_rural_15_19_year": 25.49,
      "NEET_male_rural_15_19_year": 10.57,
      "NEET_female_rural_15_19_year": 40.12,
      "NEET_urban_15_19_year": 20.35,
      "NEET_male_urban_15_19_year": 9.3,
      "NEET_female_urban_15_19_year": 31.32,
      "NEET_20_24_year_overall": 44.46,
      "NEET_male_20_24_year": 10.14,
      "NEET_female_20_24_year": 72.36,
      "NEET_rural_20_24_year": 46.3,
      "NEET_male_rural_20_24_year": 10.26,
      "NEET_female_rural_20_24_year": 75.36,
      "NEET_urban_20_24_year": 38.44,
      "NEET_male_urban_20_24_year": 9.73,
      "NEET_female_urban_20_24_year": 62.32
    },
    "Lakshmipur": {
      "NEET_Overall_15_24": 42.16,
      "NEET_male_Overall_15_24": 17.73,
      "NEET_female_Overall_15_24": 60.75,
      "NEET_rural_Overall_15_24": 43.17,
      "NEET_male_rural_Overall_15_24": 18.25,
      "NEET_female_rural_Overall_15_24": 61.8,
      "NEET_urban_Overall_15_24": 39.13,
      "NEET_male_urban_Overall_15_24": 16.23,
      "NEET_female_urban_Overall_15_24": 57.49,
      "NEET_15_19_year_overall": 31.38,
      "NEET_male_15_19_year": 18.86,
      "NEET_female_15_19_year": 42.09,
      "NEET_rural_15_19_year": 32.55,
      "NEET_male_rural_15_19_year": 19.57,
      "NEET_female_rural_15_19_year": 43.46,
      "NEET_urban_15_19_year": 27.82,
      "NEET_male_urban_15_19_year": 16.78,
      "NEET_female_urban_15_19_year": 37.79,
      "NEET_20_24_year_overall": 55.15,
      "NEET_male_20_24_year": 16.15,
      "NEET_female_20_24_year": 80.87,
      "NEET_rural_20_24_year": 56.04,
      "NEET_male_rural_20_24_year": 16.39,
      "NEET_female_rural_20_24_year": 81.72,
      "NEET_urban_20_24_year": 52.51,
      "NEET_male_urban_20_24_year": 15.47,
      "NEET_female_urban_20_24_year": 78.29
    },
    "Lalmonirhat": {
      "NEET_Overall_15_24": 34.47,
      "NEET_male_Overall_15_24": 13.79,
      "NEET_female_Overall_15_24": 53.89,
      "NEET_rural_Overall_15_24": 35.11,
      "NEET_male_rural_Overall_15_24": 14.04,
      "NEET_female_rural_Overall_15_24": 55.22,
      "NEET_urban_Overall_15_24": 32.06,
      "NEET_male_urban_Overall_15_24": 12.79,
      "NEET_female_urban_Overall_15_24": 49.01,
      "NEET_15_19_year_overall": 25.7,
      "NEET_male_15_19_year": 14.24,
      "NEET_female_15_19_year": 37.19,
      "NEET_rural_15_19_year": 26.34,
      "NEET_male_rural_15_19_year": 14.6,
      "NEET_female_rural_15_19_year": 38.31,
      "NEET_urban_15_19_year": 23.24,
      "NEET_male_urban_15_19_year": 12.82,
      "NEET_female_urban_15_19_year": 33.07,
      "NEET_20_24_year_overall": 45.3,
      "NEET_male_20_24_year": 13.18,
      "NEET_female_20_24_year": 73.07,
      "NEET_rural_20_24_year": 45.94,
      "NEET_male_rural_20_24_year": 13.29,
      "NEET_female_rural_20_24_year": 74.68,
      "NEET_urban_20_24_year": 42.88,
      "NEET_male_urban_20_24_year": 12.75,
      "NEET_female_urban_20_24_year": 67.22
    },
    "Madaripur": {
      "NEET_Overall_15_24": 37.32,
      "NEET_male_Overall_15_24": 17.12,
      "NEET_female_Overall_15_24": 53.16,
      "NEET_rural_Overall_15_24": 37.99,
      "NEET_male_rural_Overall_15_24": 17.53,
      "NEET_female_rural_Overall_15_24": 53.98,
      "NEET_urban_Overall_15_24": 35.24,
      "NEET_male_urban_Overall_15_24": 15.86,
      "NEET_female_urban_Overall_15_24": 50.58,
      "NEET_15_19_year_overall": 26.85,
      "NEET_male_15_19_year": 17.73,
      "NEET_female_15_19_year": 34.88,
      "NEET_rural_15_19_year": 27.53,
      "NEET_male_rural_15_19_year": 18.35,
      "NEET_female_rural_15_19_year": 35.58,
      "NEET_urban_15_19_year": 24.65,
      "NEET_male_urban_15_19_year": 15.78,
      "NEET_female_urban_15_19_year": 32.59,
      "NEET_20_24_year_overall": 50.32,
      "NEET_male_20_24_year": 16.25,
      "NEET_female_20_24_year": 73.41,
      "NEET_rural_20_24_year": 51.23,
      "NEET_male_rural_20_24_year": 16.34,
      "NEET_female_rural_20_24_year": 74.8,
      "NEET_urban_20_24_year": 47.6,
      "NEET_male_urban_20_24_year": 15.96,
      "NEET_female_urban_20_24_year": 69.25
    },
    "Magura": {
      "NEET_Overall_15_24": 34.64,
      "NEET_male_Overall_15_24": 11.82,
      "NEET_female_Overall_15_24": 55.84,
      "NEET_rural_Overall_15_24": 35.88,
      "NEET_male_rural_Overall_15_24": 12.34,
      "NEET_female_rural_Overall_15_24": 57.71,
      "NEET_urban_Overall_15_24": 29.65,
      "NEET_male_urban_Overall_15_24": 9.73,
      "NEET_female_urban_Overall_15_24": 48.24,
      "NEET_15_19_year_overall": 25.11,
      "NEET_male_15_19_year": 11.78,
      "NEET_female_15_19_year": 38.72,
      "NEET_rural_15_19_year": 26.06,
      "NEET_male_rural_15_19_year": 12.42,
      "NEET_female_rural_15_19_year": 40.03,
      "NEET_urban_15_19_year": 21.23,
      "NEET_male_urban_15_19_year": 9.17,
      "NEET_female_urban_15_19_year": 33.4,
      "NEET_20_24_year_overall": 45.76,
      "NEET_male_20_24_year": 11.87,
      "NEET_female_20_24_year": 73.92,
      "NEET_rural_20_24_year": 47.37,
      "NEET_male_rural_20_24_year": 12.23,
      "NEET_female_rural_20_24_year": 76.38,
      "NEET_urban_20_24_year": 39.31,
      "NEET_male_urban_20_24_year": 10.43,
      "NEET_female_urban_20_24_year": 63.94
    },
    "Manikganj": {
      "NEET_Overall_15_24": 36.03,
      "NEET_male_Overall_15_24": 14.77,
      "NEET_female_Overall_15_24": 53.96,
      "NEET_rural_Overall_15_24": 37.09,
      "NEET_male_rural_Overall_15_24": 15.3,
      "NEET_female_rural_Overall_15_24": 55.56,
      "NEET_urban_Overall_15_24": 30.13,
      "NEET_male_urban_Overall_15_24": 11.78,
      "NEET_female_urban_Overall_15_24": 45.17,
      "NEET_15_19_year_overall": 27.24,
      "NEET_male_15_19_year": 14.99,
      "NEET_female_15_19_year": 38.66,
      "NEET_rural_15_19_year": 28.22,
      "NEET_male_rural_15_19_year": 15.62,
      "NEET_female_rural_15_19_year": 40.04,
      "NEET_urban_15_19_year": 21.73,
      "NEET_male_urban_15_19_year": 11.41,
      "NEET_female_urban_15_19_year": 31.02,
      "NEET_20_24_year_overall": 46.45,
      "NEET_male_20_24_year": 14.47,
      "NEET_female_20_24_year": 70.37,
      "NEET_rural_20_24_year": 47.64,
      "NEET_male_rural_20_24_year": 14.87,
      "NEET_female_rural_20_24_year": 72.25,
      "NEET_urban_20_24_year": 39.91,
      "NEET_male_urban_20_24_year": 12.26,
      "NEET_female_urban_20_24_year": 60.16
    },
    "Meherpur": {
      "NEET_Overall_15_24": 37.6,
      "NEET_male_Overall_15_24": 12.19,
      "NEET_female_Overall_15_24": 59.61,
      "NEET_rural_Overall_15_24": 38.46,
      "NEET_male_rural_Overall_15_24": 12.51,
      "NEET_female_rural_Overall_15_24": 61.15,
      "NEET_urban_Overall_15_24": 34.64,
      "NEET_male_urban_Overall_15_24": 11.07,
      "NEET_female_urban_Overall_15_24": 54.42,
      "NEET_15_19_year_overall": 28.98,
      "NEET_male_15_19_year": 12.3,
      "NEET_female_15_19_year": 44.45,
      "NEET_rural_15_19_year": 30.05,
      "NEET_male_rural_15_19_year": 12.79,
      "NEET_female_rural_15_19_year": 46.13,
      "NEET_urban_15_19_year": 25.23,
      "NEET_male_urban_15_19_year": 10.53,
      "NEET_female_urban_15_19_year": 38.63,
      "NEET_20_24_year_overall": 47.9,
      "NEET_male_20_24_year": 12.06,
      "NEET_female_20_24_year": 76.54,
      "NEET_rural_20_24_year": 48.6,
      "NEET_male_rural_20_24_year": 12.14,
      "NEET_female_rural_20_24_year": 78.15,
      "NEET_urban_20_24_year": 45.54,
      "NEET_male_urban_20_24_year": 11.76,
      "NEET_female_urban_20_24_year": 71.27
    },
    "Moulvibazar": {
      "NEET_Overall_15_24": 36.36,
      "NEET_male_Overall_15_24": 17.38,
      "NEET_female_Overall_15_24": 52.36,
      "NEET_rural_Overall_15_24": 36.95,
      "NEET_male_rural_Overall_15_24": 17.77,
      "NEET_female_rural_Overall_15_24": 53.1,
      "NEET_urban_Overall_15_24": 32.7,
      "NEET_male_urban_Overall_15_24": 15.01,
      "NEET_female_urban_Overall_15_24": 47.84,
      "NEET_15_19_year_overall": 28.01,
      "NEET_male_15_19_year": 18.92,
      "NEET_female_15_19_year": 36.41,
      "NEET_rural_15_19_year": 28.64,
      "NEET_male_rural_15_19_year": 19.4,
      "NEET_female_rural_15_19_year": 37.14,
      "NEET_urban_15_19_year": 24,
      "NEET_male_urban_15_19_year": 15.92,
      "NEET_female_urban_15_19_year": 31.69,
      "NEET_20_24_year_overall": 46.42,
      "NEET_male_20_24_year": 15.3,
      "NEET_female_20_24_year": 69.87,
      "NEET_rural_20_24_year": 47.11,
      "NEET_male_rural_20_24_year": 15.55,
      "NEET_female_rural_20_24_year": 70.87,
      "NEET_urban_20_24_year": 42.4,
      "NEET_male_urban_20_24_year": 13.87,
      "NEET_female_urban_20_24_year": 64.03
    },
    "Munshiganj": {
      "NEET_Overall_15_24": 37.86,
      "NEET_male_Overall_15_24": 16.53,
      "NEET_female_Overall_15_24": 56.1,
      "NEET_rural_Overall_15_24": 38.52,
      "NEET_male_rural_Overall_15_24": 17.16,
      "NEET_female_rural_Overall_15_24": 56.5,
      "NEET_urban_Overall_15_24": 35.04,
      "NEET_male_urban_Overall_15_24": 13.96,
      "NEET_female_urban_Overall_15_24": 54.34,
      "NEET_15_19_year_overall": 27.46,
      "NEET_male_15_19_year": 16.28,
      "NEET_female_15_19_year": 37.96,
      "NEET_rural_15_19_year": 27.72,
      "NEET_male_rural_15_19_year": 16.66,
      "NEET_female_rural_15_19_year": 38.03,
      "NEET_urban_15_19_year": 26.31,
      "NEET_male_urban_15_19_year": 14.65,
      "NEET_female_urban_15_19_year": 37.63,
      "NEET_20_24_year_overall": 50,
      "NEET_male_20_24_year": 16.85,
      "NEET_female_20_24_year": 75.41,
      "NEET_rural_20_24_year": 51.25,
      "NEET_male_rural_20_24_year": 17.81,
      "NEET_female_rural_20_24_year": 76.18,
      "NEET_urban_20_24_year": 44.82,
      "NEET_male_urban_20_24_year": 13.14,
      "NEET_female_urban_20_24_year": 72.01
    },
    "Mymensingh": {
      "NEET_Overall_15_24": 35.36,
      "NEET_male_Overall_15_24": 14.33,
      "NEET_female_Overall_15_24": 53.19,
      "NEET_rural_Overall_15_24": 37.64,
      "NEET_male_rural_Overall_15_24": 15.53,
      "NEET_female_rural_Overall_15_24": 55.95,
      "NEET_urban_Overall_15_24": 28.75,
      "NEET_male_urban_Overall_15_24": 11.01,
      "NEET_female_urban_Overall_15_24": 44.82,
      "NEET_15_19_year_overall": 26.72,
      "NEET_male_15_19_year": 15.45,
      "NEET_female_15_19_year": 37.36,
      "NEET_rural_15_19_year": 28.51,
      "NEET_male_rural_15_19_year": 16.88,
      "NEET_female_rural_15_19_year": 39.22,
      "NEET_urban_15_19_year": 21.4,
      "NEET_male_urban_15_19_year": 11.36,
      "NEET_female_urban_15_19_year": 31.57,
      "NEET_20_24_year_overall": 45.2,
      "NEET_male_20_24_year": 12.88,
      "NEET_female_20_24_year": 69.41,
      "NEET_rural_20_24_year": 48.21,
      "NEET_male_rural_20_24_year": 13.74,
      "NEET_female_rural_20_24_year": 73.39,
      "NEET_urban_20_24_year": 36.74,
      "NEET_male_urban_20_24_year": 10.58,
      "NEET_female_urban_20_24_year": 57.75
    },
    "Naogaon": {
      "NEET_Overall_15_24": 38.09,
      "NEET_male_Overall_15_24": 13.31,
      "NEET_female_Overall_15_24": 60.33,
      "NEET_rural_Overall_15_24": 39.56,
      "NEET_male_rural_Overall_15_24": 13.99,
      "NEET_female_rural_Overall_15_24": 62.32,
      "NEET_urban_Overall_15_24": 30.51,
      "NEET_male_urban_Overall_15_24": 9.9,
      "NEET_female_urban_Overall_15_24": 49.78,
      "NEET_15_19_year_overall": 28.87,
      "NEET_male_15_19_year": 12.76,
      "NEET_female_15_19_year": 44.41,
      "NEET_rural_15_19_year": 30.35,
      "NEET_male_rural_15_19_year": 13.46,
      "NEET_female_rural_15_19_year": 46.47,
      "NEET_urban_15_19_year": 21.36,
      "NEET_male_urban_15_19_year": 9.25,
      "NEET_female_urban_15_19_year": 33.62,
      "NEET_20_24_year_overall": 48.29,
      "NEET_male_20_24_year": 13.98,
      "NEET_female_20_24_year": 76.73,
      "NEET_rural_20_24_year": 49.7,
      "NEET_male_rural_20_24_year": 14.62,
      "NEET_female_rural_20_24_year": 78.62,
      "NEET_urban_20_24_year": 40.87,
      "NEET_male_urban_20_24_year": 10.7,
      "NEET_female_urban_20_24_year": 66.65
    },
    "Narail": {
      "NEET_Overall_15_24": 36.61,
      "NEET_male_Overall_15_24": 13.1,
      "NEET_female_Overall_15_24": 56.9,
      "NEET_rural_Overall_15_24": 37.44,
      "NEET_male_rural_Overall_15_24": 13.48,
      "NEET_female_rural_Overall_15_24": 58.02,
      "NEET_urban_Overall_15_24": 33.71,
      "NEET_male_urban_Overall_15_24": 11.81,
      "NEET_female_urban_Overall_15_24": 52.94,
      "NEET_15_19_year_overall": 26.76,
      "NEET_male_15_19_year": 12.92,
      "NEET_female_15_19_year": 39.93,
      "NEET_rural_15_19_year": 27.39,
      "NEET_male_rural_15_19_year": 13.24,
      "NEET_female_rural_15_19_year": 40.8,
      "NEET_urban_15_19_year": 24.56,
      "NEET_male_urban_15_19_year": 11.77,
      "NEET_female_urban_15_19_year": 36.84,
      "NEET_20_24_year_overall": 48.47,
      "NEET_male_20_24_year": 13.35,
      "NEET_female_20_24_year": 75.4,
      "NEET_rural_20_24_year": 49.58,
      "NEET_male_rural_20_24_year": 13.79,
      "NEET_female_rural_20_24_year": 76.81,
      "NEET_urban_20_24_year": 44.61,
      "NEET_male_urban_20_24_year": 11.85,
      "NEET_female_urban_20_24_year": 70.42
    },
    "Narayanganj": {
      "NEET_Overall_15_24": 31.48,
      "NEET_male_Overall_15_24": 10.03,
      "NEET_female_Overall_15_24": 50.95,
      "NEET_rural_Overall_15_24": 31.62,
      "NEET_male_rural_Overall_15_24": 9.87,
      "NEET_female_rural_Overall_15_24": 51.49,
      "NEET_urban_Overall_15_24": 31.27,
      "NEET_male_urban_Overall_15_24": 10.26,
      "NEET_female_urban_Overall_15_24": 50.16,
      "NEET_15_19_year_overall": 25.58,
      "NEET_male_15_19_year": 11.97,
      "NEET_female_15_19_year": 38.2,
      "NEET_rural_15_19_year": 25.95,
      "NEET_male_rural_15_19_year": 11.99,
      "NEET_female_rural_15_19_year": 38.94,
      "NEET_urban_15_19_year": 25.03,
      "NEET_male_urban_15_19_year": 11.94,
      "NEET_female_urban_15_19_year": 37.12,
      "NEET_20_24_year_overall": 37.31,
      "NEET_male_20_24_year": 8.06,
      "NEET_female_20_24_year": 63.32,
      "NEET_rural_20_24_year": 37.26,
      "NEET_male_rural_20_24_year": 7.72,
      "NEET_female_rural_20_24_year": 63.78,
      "NEET_urban_20_24_year": 37.39,
      "NEET_male_urban_20_24_year": 8.56,
      "NEET_female_urban_20_24_year": 62.66
    },
    "Narsingdi": {
      "NEET_Overall_15_24": 35.76,
      "NEET_male_Overall_15_24": 14.85,
      "NEET_female_Overall_15_24": 54.27,
      "NEET_rural_Overall_15_24": 36.72,
      "NEET_male_rural_Overall_15_24": 15.61,
      "NEET_female_rural_Overall_15_24": 55.09,
      "NEET_urban_Overall_15_24": 32.95,
      "NEET_male_urban_Overall_15_24": 12.68,
      "NEET_female_urban_Overall_15_24": 51.83,
      "NEET_15_19_year_overall": 27.34,
      "NEET_male_15_19_year": 16.29,
      "NEET_female_15_19_year": 37.95,
      "NEET_rural_15_19_year": 28.11,
      "NEET_male_rural_15_19_year": 17.16,
      "NEET_female_rural_15_19_year": 38.53,
      "NEET_urban_15_19_year": 25.02,
      "NEET_male_urban_15_19_year": 13.76,
      "NEET_female_urban_15_19_year": 36.19,
      "NEET_20_24_year_overall": 45.57,
      "NEET_male_20_24_year": 13,
      "NEET_female_20_24_year": 71.75,
      "NEET_rural_20_24_year": 46.84,
      "NEET_male_rural_20_24_year": 13.6,
      "NEET_female_rural_20_24_year": 72.85,
      "NEET_urban_20_24_year": 41.95,
      "NEET_male_urban_20_24_year": 11.37,
      "NEET_female_urban_20_24_year": 68.44
    },
    "Natore": {
      "NEET_Overall_15_24": 35.77,
      "NEET_male_Overall_15_24": 10.96,
      "NEET_female_Overall_15_24": 58.19,
      "NEET_rural_Overall_15_24": 36.77,
      "NEET_male_rural_Overall_15_24": 11.37,
      "NEET_female_rural_Overall_15_24": 59.73,
      "NEET_urban_Overall_15_24": 31.76,
      "NEET_male_urban_Overall_15_24": 9.32,
      "NEET_female_urban_Overall_15_24": 51.99,
      "NEET_15_19_year_overall": 27.09,
      "NEET_male_15_19_year": 11.01,
      "NEET_female_15_19_year": 42.72,
      "NEET_rural_15_19_year": 27.98,
      "NEET_male_rural_15_19_year": 11.4,
      "NEET_female_rural_15_19_year": 44.13,
      "NEET_urban_15_19_year": 23.48,
      "NEET_male_urban_15_19_year": 9.42,
      "NEET_female_urban_15_19_year": 37,
      "NEET_20_24_year_overall": 45.66,
      "NEET_male_20_24_year": 10.9,
      "NEET_female_20_24_year": 74.56,
      "NEET_rural_20_24_year": 46.84,
      "NEET_male_rural_20_24_year": 11.33,
      "NEET_female_rural_20_24_year": 76.3,
      "NEET_urban_20_24_year": 40.99,
      "NEET_male_urban_20_24_year": 9.2,
      "NEET_female_urban_20_24_year": 67.63
    },
    "Netrakona": {
      "NEET_Overall_15_24": 36.56,
      "NEET_male_Overall_15_24": 15.47,
      "NEET_female_Overall_15_24": 54.4,
      "NEET_rural_Overall_15_24": 37.95,
      "NEET_male_rural_Overall_15_24": 16.2,
      "NEET_female_rural_Overall_15_24": 56.16,
      "NEET_urban_Overall_15_24": 29.54,
      "NEET_male_urban_Overall_15_24": 11.87,
      "NEET_female_urban_Overall_15_24": 45.25,
      "NEET_15_19_year_overall": 27.2,
      "NEET_male_15_19_year": 16.79,
      "NEET_female_15_19_year": 37.21,
      "NEET_rural_15_19_year": 28.45,
      "NEET_male_rural_15_19_year": 17.7,
      "NEET_female_rural_15_19_year": 38.73,
      "NEET_urban_15_19_year": 20.88,
      "NEET_male_urban_15_19_year": 12.23,
      "NEET_female_urban_15_19_year": 29.44,
      "NEET_20_24_year_overall": 48.2,
      "NEET_male_20_24_year": 13.55,
      "NEET_female_20_24_year": 73.14,
      "NEET_rural_20_24_year": 49.77,
      "NEET_male_rural_20_24_year": 14,
      "NEET_female_rural_20_24_year": 75.12,
      "NEET_urban_20_24_year": 40.28,
      "NEET_male_urban_20_24_year": 11.37,
      "NEET_female_urban_20_24_year": 62.79
    },
    "Nilphamari": {
      "NEET_Overall_15_24": 32.73,
      "NEET_male_Overall_15_24": 11.51,
      "NEET_female_Overall_15_24": 51.44,
      "NEET_rural_Overall_15_24": 33.44,
      "NEET_male_rural_Overall_15_24": 11.58,
      "NEET_female_rural_Overall_15_24": 52.62,
      "NEET_urban_Overall_15_24": 30.73,
      "NEET_male_urban_Overall_15_24": 11.32,
      "NEET_female_urban_Overall_15_24": 48.11,
      "NEET_15_19_year_overall": 23.79,
      "NEET_male_15_19_year": 11.65,
      "NEET_female_15_19_year": 35.54,
      "NEET_rural_15_19_year": 24.52,
      "NEET_male_rural_15_19_year": 11.89,
      "NEET_female_rural_15_19_year": 36.68,
      "NEET_urban_15_19_year": 21.71,
      "NEET_male_urban_15_19_year": 10.98,
      "NEET_female_urban_15_19_year": 32.27,
      "NEET_20_24_year_overall": 43.65,
      "NEET_male_20_24_year": 11.32,
      "NEET_female_20_24_year": 69.07,
      "NEET_rural_20_24_year": 44.37,
      "NEET_male_rural_20_24_year": 11.16,
      "NEET_female_rural_20_24_year": 70.34,
      "NEET_urban_20_24_year": 41.66,
      "NEET_male_urban_20_24_year": 11.77,
      "NEET_female_urban_20_24_year": 65.5
    },
    "Noakhali": {
      "NEET_Overall_15_24": 41.64,
      "NEET_male_Overall_15_24": 18.62,
      "NEET_female_Overall_15_24": 59.89,
      "NEET_rural_Overall_15_24": 42.92,
      "NEET_male_rural_Overall_15_24": 19.31,
      "NEET_female_rural_Overall_15_24": 61.28,
      "NEET_urban_Overall_15_24": 35.95,
      "NEET_male_urban_Overall_15_24": 15.69,
      "NEET_female_urban_Overall_15_24": 53.4,
      "NEET_15_19_year_overall": 31.31,
      "NEET_male_15_19_year": 19.37,
      "NEET_female_15_19_year": 41.69,
      "NEET_rural_15_19_year": 32.57,
      "NEET_male_rural_15_19_year": 20.26,
      "NEET_female_rural_15_19_year": 43.09,
      "NEET_urban_15_19_year": 25.57,
      "NEET_male_urban_15_19_year": 15.45,
      "NEET_female_urban_15_19_year": 35,
      "NEET_20_24_year_overall": 53.34,
      "NEET_male_20_24_year": 17.67,
      "NEET_female_20_24_year": 78.8,
      "NEET_rural_20_24_year": 54.75,
      "NEET_male_rural_20_24_year": 18.09,
      "NEET_female_rural_20_24_year": 80.31,
      "NEET_urban_20_24_year": 47.22,
      "NEET_male_urban_20_24_year": 15.96,
      "NEET_female_urban_20_24_year": 71.88
    },
    "Pabna": {
      "NEET_Overall_15_24": 33.97,
      "NEET_male_Overall_15_24": 10.64,
      "NEET_female_Overall_15_24": 55.12,
      "NEET_rural_Overall_15_24": 35.28,
      "NEET_male_rural_Overall_15_24": 10.9,
      "NEET_female_rural_Overall_15_24": 57.23,
      "NEET_urban_Overall_15_24": 29.58,
      "NEET_male_urban_Overall_15_24": 9.78,
      "NEET_female_urban_Overall_15_24": 47.92,
      "NEET_15_19_year_overall": 25.35,
      "NEET_male_15_19_year": 11.27,
      "NEET_female_15_19_year": 39.37,
      "NEET_rural_15_19_year": 26.42,
      "NEET_male_rural_15_19_year": 11.67,
      "NEET_female_rural_15_19_year": 41.05,
      "NEET_urban_15_19_year": 21.66,
      "NEET_male_urban_15_19_year": 9.9,
      "NEET_female_urban_15_19_year": 33.5,
      "NEET_20_24_year_overall": 44.16,
      "NEET_male_20_24_year": 9.81,
      "NEET_female_20_24_year": 71.99,
      "NEET_rural_20_24_year": 45.94,
      "NEET_male_rural_20_24_year": 9.86,
      "NEET_female_rural_20_24_year": 74.81,
      "NEET_urban_20_24_year": 38.41,
      "NEET_male_urban_20_24_year": 9.63,
      "NEET_female_urban_20_24_year": 62.69
    },
    "Panchagarh": {
      "NEET_Overall_15_24": 35.14,
      "NEET_male_Overall_15_24": 11.73,
      "NEET_female_Overall_15_24": 55.73,
      "NEET_rural_Overall_15_24": 35.63,
      "NEET_male_rural_Overall_15_24": 11.82,
      "NEET_female_rural_Overall_15_24": 56.69,
      "NEET_urban_Overall_15_24": 32.65,
      "NEET_male_urban_Overall_15_24": 11.28,
      "NEET_female_urban_Overall_15_24": 50.91,
      "NEET_15_19_year_overall": 25.08,
      "NEET_male_15_19_year": 11.61,
      "NEET_female_15_19_year": 38.01,
      "NEET_rural_15_19_year": 25.54,
      "NEET_male_rural_15_19_year": 11.69,
      "NEET_female_rural_15_19_year": 38.9,
      "NEET_urban_15_19_year": 22.77,
      "NEET_male_urban_15_19_year": 11.22,
      "NEET_female_urban_15_19_year": 33.56,
      "NEET_20_24_year_overall": 47.1,
      "NEET_male_20_24_year": 11.89,
      "NEET_female_20_24_year": 75.01,
      "NEET_rural_20_24_year": 47.61,
      "NEET_male_rural_20_24_year": 11.99,
      "NEET_female_rural_20_24_year": 76.04,
      "NEET_urban_20_24_year": 44.47,
      "NEET_male_urban_20_24_year": 11.36,
      "NEET_female_urban_20_24_year": 69.87
    },
    "Patuakhali": {
      "NEET_Overall_15_24": 35.7,
      "NEET_male_Overall_15_24": 13.69,
      "NEET_female_Overall_15_24": 54.16,
      "NEET_rural_Overall_15_24": 36.58,
      "NEET_male_rural_Overall_15_24": 14.01,
      "NEET_female_rural_Overall_15_24": 55.5,
      "NEET_urban_Overall_15_24": 31.93,
      "NEET_male_urban_Overall_15_24": 12.32,
      "NEET_female_urban_Overall_15_24": 48.46,
      "NEET_15_19_year_overall": 26.27,
      "NEET_male_15_19_year": 14.25,
      "NEET_female_15_19_year": 37.37,
      "NEET_rural_15_19_year": 27.1,
      "NEET_male_rural_15_19_year": 14.74,
      "NEET_female_rural_15_19_year": 38.46,
      "NEET_urban_15_19_year": 22.62,
      "NEET_male_urban_15_19_year": 12.1,
      "NEET_female_urban_15_19_year": 32.51,
      "NEET_20_24_year_overall": 46.87,
      "NEET_male_20_24_year": 12.94,
      "NEET_female_20_24_year": 72.28,
      "NEET_rural_20_24_year": 47.98,
      "NEET_male_rural_20_24_year": 13.03,
      "NEET_female_rural_20_24_year": 74.18,
      "NEET_urban_20_24_year": 42.34,
      "NEET_male_urban_20_24_year": 12.61,
      "NEET_female_urban_20_24_year": 64.51
    },
    "Pirojpur": {
      "NEET_Overall_15_24": 35.34,
      "NEET_male_Overall_15_24": 15.11,
      "NEET_female_Overall_15_24": 52.8,
      "NEET_rural_Overall_15_24": 36.37,
      "NEET_male_rural_Overall_15_24": 15.68,
      "NEET_female_rural_Overall_15_24": 53.9,
      "NEET_urban_Overall_15_24": 31.48,
      "NEET_male_urban_Overall_15_24": 13.06,
      "NEET_female_urban_Overall_15_24": 48.46,
      "NEET_15_19_year_overall": 25.06,
      "NEET_male_15_19_year": 14.97,
      "NEET_female_15_19_year": 34.68,
      "NEET_rural_15_19_year": 25.94,
      "NEET_male_rural_15_19_year": 15.66,
      "NEET_female_rural_15_19_year": 35.55,
      "NEET_urban_15_19_year": 21.72,
      "NEET_male_urban_15_19_year": 12.47,
      "NEET_female_urban_15_19_year": 31.2,
      "NEET_20_24_year_overall": 47.65,
      "NEET_male_20_24_year": 15.31,
      "NEET_female_20_24_year": 72.39,
      "NEET_rural_20_24_year": 48.91,
      "NEET_male_rural_20_24_year": 15.72,
      "NEET_female_rural_20_24_year": 73.87,
      "NEET_urban_20_24_year": 42.97,
      "NEET_male_urban_20_24_year": 13.85,
      "NEET_female_urban_20_24_year": 66.68
    },
    "Rajbari": {
      "NEET_Overall_15_24": 35.69,
      "NEET_male_Overall_15_24": 12.52,
      "NEET_female_Overall_15_24": 55.09,
      "NEET_rural_Overall_15_24": 36.63,
      "NEET_male_rural_Overall_15_24": 12.7,
      "NEET_female_rural_Overall_15_24": 56.65,
      "NEET_urban_Overall_15_24": 30.52,
      "NEET_male_urban_Overall_15_24": 11.5,
      "NEET_female_urban_Overall_15_24": 46.51,
      "NEET_15_19_year_overall": 25.17,
      "NEET_male_15_19_year": 12.54,
      "NEET_female_15_19_year": 36.91,
      "NEET_rural_15_19_year": 25.99,
      "NEET_male_rural_15_19_year": 12.87,
      "NEET_female_rural_15_19_year": 38.17,
      "NEET_urban_15_19_year": 20.56,
      "NEET_male_urban_15_19_year": 10.72,
      "NEET_female_urban_15_19_year": 29.78,
      "NEET_20_24_year_overall": 47.96,
      "NEET_male_20_24_year": 12.48,
      "NEET_female_20_24_year": 74.22,
      "NEET_rural_20_24_year": 49.15,
      "NEET_male_rural_20_24_year": 12.48,
      "NEET_female_rural_20_24_year": 76.25,
      "NEET_urban_20_24_year": 41.62,
      "NEET_male_urban_20_24_year": 12.48,
      "NEET_female_urban_20_24_year": 63.33
    },
    "Rajshahi": {
      "NEET_Overall_15_24": 30.24,
      "NEET_male_Overall_15_24": 8.58,
      "NEET_female_Overall_15_24": 51.6,
      "NEET_rural_Overall_15_24": 34.76,
      "NEET_male_rural_Overall_15_24": 9.5,
      "NEET_female_rural_Overall_15_24": 58.68,
      "NEET_urban_Overall_15_24": 24.2,
      "NEET_male_urban_Overall_15_24": 7.4,
      "NEET_female_urban_Overall_15_24": 41.68,
      "NEET_15_19_year_overall": 23.59,
      "NEET_male_15_19_year": 8.66,
      "NEET_female_15_19_year": 38.78,
      "NEET_rural_15_19_year": 26.75,
      "NEET_male_rural_15_19_year": 9.47,
      "NEET_female_rural_15_19_year": 43.69,
      "NEET_urban_15_19_year": 18.87,
      "NEET_male_urban_15_19_year": 7.5,
      "NEET_female_urban_15_19_year": 31.12,
      "NEET_20_24_year_overall": 36.99,
      "NEET_male_20_24_year": 8.49,
      "NEET_female_20_24_year": 64.2,
      "NEET_rural_20_24_year": 43.67,
      "NEET_male_rural_20_24_year": 9.53,
      "NEET_female_rural_20_24_year": 74.8,
      "NEET_urban_20_24_year": 28.97,
      "NEET_male_urban_20_24_year": 7.31,
      "NEET_female_urban_20_24_year": 50.83
    },
    "Rangamati": {
      "NEET_Overall_15_24": 31.11,
      "NEET_male_Overall_15_24": 13.42,
      "NEET_female_Overall_15_24": 49.3,
      "NEET_rural_Overall_15_24": 34.17,
      "NEET_male_rural_Overall_15_24": 15.05,
      "NEET_female_rural_Overall_15_24": 53.74,
      "NEET_urban_Overall_15_24": 27.96,
      "NEET_male_urban_Overall_15_24": 11.75,
      "NEET_female_urban_Overall_15_24": 44.7,
      "NEET_15_19_year_overall": 24.26,
      "NEET_male_15_19_year": 15.01,
      "NEET_female_15_19_year": 33.87,
      "NEET_rural_15_19_year": 27.21,
      "NEET_male_rural_15_19_year": 16.78,
      "NEET_female_rural_15_19_year": 38.16,
      "NEET_urban_15_19_year": 21.12,
      "NEET_male_urban_15_19_year": 13.1,
      "NEET_female_urban_15_19_year": 29.35,
      "NEET_20_24_year_overall": 38.42,
      "NEET_male_20_24_year": 11.71,
      "NEET_female_20_24_year": 65.57,
      "NEET_rural_20_24_year": 41.83,
      "NEET_male_rural_20_24_year": 13.09,
      "NEET_female_rural_20_24_year": 70.46,
      "NEET_urban_20_24_year": 35.01,
      "NEET_male_urban_20_24_year": 10.36,
      "NEET_female_urban_20_24_year": 60.6
    },
    "Rangpur": {
      "NEET_Overall_15_24": 31.75,
      "NEET_male_Overall_15_24": 11.78,
      "NEET_female_Overall_15_24": 49.87,
      "NEET_rural_Overall_15_24": 34.98,
      "NEET_male_rural_Overall_15_24": 13.22,
      "NEET_female_rural_Overall_15_24": 53.9,
      "NEET_urban_Overall_15_24": 26.38,
      "NEET_male_urban_Overall_15_24": 9.54,
      "NEET_female_urban_Overall_15_24": 42.79,
      "NEET_15_19_year_overall": 22.51,
      "NEET_male_15_19_year": 11.44,
      "NEET_female_15_19_year": 33.7,
      "NEET_rural_15_19_year": 24.83,
      "NEET_male_rural_15_19_year": 12.9,
      "NEET_female_rural_15_19_year": 36.44,
      "NEET_urban_15_19_year": 18.43,
      "NEET_male_urban_15_19_year": 9.03,
      "NEET_female_urban_15_19_year": 28.62,
      "NEET_20_24_year_overall": 43.17,
      "NEET_male_20_24_year": 12.26,
      "NEET_female_20_24_year": 67.65,
      "NEET_rural_20_24_year": 48.1,
      "NEET_male_rural_20_24_year": 13.7,
      "NEET_female_rural_20_24_year": 73.9,
      "NEET_urban_20_24_year": 35.5,
      "NEET_male_urban_20_24_year": 10.19,
      "NEET_female_urban_20_24_year": 57.3
    },
    "Satkhira": {
      "NEET_Overall_15_24": 37.67,
      "NEET_male_Overall_15_24": 11.79,
      "NEET_female_Overall_15_24": 60.91,
      "NEET_rural_Overall_15_24": 38.44,
      "NEET_male_rural_Overall_15_24": 12.08,
      "NEET_female_rural_Overall_15_24": 62.3,
      "NEET_urban_Overall_15_24": 34.62,
      "NEET_male_urban_Overall_15_24": 10.65,
      "NEET_female_urban_Overall_15_24": 55.51,
      "NEET_15_19_year_overall": 29.31,
      "NEET_male_15_19_year": 12.58,
      "NEET_female_15_19_year": 45.21,
      "NEET_rural_15_19_year": 30.02,
      "NEET_male_rural_15_19_year": 12.95,
      "NEET_female_rural_15_19_year": 46.38,
      "NEET_urban_15_19_year": 26.44,
      "NEET_male_urban_15_19_year": 11.03,
      "NEET_female_urban_15_19_year": 40.59,
      "NEET_20_24_year_overall": 46.47,
      "NEET_male_20_24_year": 10.92,
      "NEET_female_20_24_year": 76.58,
      "NEET_rural_20_24_year": 47.38,
      "NEET_male_rural_20_24_year": 11.09,
      "NEET_female_rural_20_24_year": 78.3,
      "NEET_urban_20_24_year": 42.96,
      "NEET_male_urban_20_24_year": 10.24,
      "NEET_female_urban_20_24_year": 70
    },
    "Shariatpur": {
      "NEET_Overall_15_24": 38.61,
      "NEET_male_Overall_15_24": 17.86,
      "NEET_female_Overall_15_24": 55.02,
      "NEET_rural_Overall_15_24": 39.28,
      "NEET_male_rural_Overall_15_24": 18.25,
      "NEET_female_rural_Overall_15_24": 55.74,
      "NEET_urban_Overall_15_24": 36.47,
      "NEET_male_urban_Overall_15_24": 16.68,
      "NEET_female_urban_Overall_15_24": 52.7,
      "NEET_15_19_year_overall": 28.38,
      "NEET_male_15_19_year": 19.05,
      "NEET_female_15_19_year": 36.4,
      "NEET_rural_15_19_year": 29.21,
      "NEET_male_rural_15_19_year": 19.7,
      "NEET_female_rural_15_19_year": 37.33,
      "NEET_urban_15_19_year": 25.73,
      "NEET_male_urban_15_19_year": 16.99,
      "NEET_female_urban_15_19_year": 33.38,
      "NEET_20_24_year_overall": 50.71,
      "NEET_male_20_24_year": 16.3,
      "NEET_female_20_24_year": 75.35,
      "NEET_rural_20_24_year": 51.32,
      "NEET_male_rural_20_24_year": 16.3,
      "NEET_female_rural_20_24_year": 75.93,
      "NEET_urban_20_24_year": 48.81,
      "NEET_male_urban_20_24_year": 16.29,
      "NEET_female_urban_20_24_year": 73.5
    },
    "Sherpur": {
      "NEET_Overall_15_24": 35.84,
      "NEET_male_Overall_15_24": 13.8,
      "NEET_female_Overall_15_24": 54.35,
      "NEET_rural_Overall_15_24": 37.22,
      "NEET_male_rural_Overall_15_24": 14.51,
      "NEET_female_rural_Overall_15_24": 56.24,
      "NEET_urban_Overall_15_24": 31.95,
      "NEET_male_urban_Overall_15_24": 11.85,
      "NEET_female_urban_Overall_15_24": 49.04,
      "NEET_15_19_year_overall": 26.31,
      "NEET_male_15_19_year": 14.1,
      "NEET_female_15_19_year": 38.1,
      "NEET_rural_15_19_year": 27.58,
      "NEET_male_rural_15_19_year": 14.89,
      "NEET_female_rural_15_19_year": 39.88,
      "NEET_urban_15_19_year": 22.78,
      "NEET_male_urban_15_19_year": 11.89,
      "NEET_female_urban_15_19_year": 33.15,
      "NEET_20_24_year_overall": 47.82,
      "NEET_male_20_24_year": 13.35,
      "NEET_female_20_24_year": 72.1,
      "NEET_rural_20_24_year": 49.35,
      "NEET_male_rural_20_24_year": 13.93,
      "NEET_female_rural_20_24_year": 73.91,
      "NEET_urban_20_24_year": 43.52,
      "NEET_male_urban_20_24_year": 11.78,
      "NEET_female_urban_20_24_year": 66.9
    },
    "Sirajganj": {
      "NEET_Overall_15_24": 32.56,
      "NEET_male_Overall_15_24": 9.53,
      "NEET_female_Overall_15_24": 53.69,
      "NEET_rural_Overall_15_24": 33.56,
      "NEET_male_rural_Overall_15_24": 9.7,
      "NEET_female_rural_Overall_15_24": 55.38,
      "NEET_urban_Overall_15_24": 28.99,
      "NEET_male_urban_Overall_15_24": 8.94,
      "NEET_female_urban_Overall_15_24": 47.61,
      "NEET_15_19_year_overall": 23.63,
      "NEET_male_15_19_year": 9.98,
      "NEET_female_15_19_year": 37.72,
      "NEET_rural_15_19_year": 24.53,
      "NEET_male_rural_15_19_year": 10.25,
      "NEET_female_rural_15_19_year": 39.3,
      "NEET_urban_15_19_year": 20.35,
      "NEET_male_urban_15_19_year": 8.99,
      "NEET_female_urban_15_19_year": 32.01,
      "NEET_20_24_year_overall": 43.79,
      "NEET_male_20_24_year": 8.88,
      "NEET_female_20_24_year": 71.37,
      "NEET_rural_20_24_year": 45.01,
      "NEET_male_rural_20_24_year": 8.88,
      "NEET_female_rural_20_24_year": 73.22,
      "NEET_urban_20_24_year": 39.53,
      "NEET_male_urban_20_24_year": 8.88,
      "NEET_female_urban_20_24_year": 64.73
    },
    "Sunamganj": {
      "NEET_Overall_15_24": 40.91,
      "NEET_male_Overall_15_24": 21.93,
      "NEET_female_Overall_15_24": 57.9,
      "NEET_rural_Overall_15_24": 41.54,
      "NEET_male_rural_Overall_15_24": 22.29,
      "NEET_female_rural_Overall_15_24": 58.85,
      "NEET_urban_Overall_15_24": 37.35,
      "NEET_male_urban_Overall_15_24": 19.88,
      "NEET_female_urban_Overall_15_24": 52.65,
      "NEET_15_19_year_overall": 34.73,
      "NEET_male_15_19_year": 24.98,
      "NEET_female_15_19_year": 44.09,
      "NEET_rural_15_19_year": 35.52,
      "NEET_male_rural_15_19_year": 25.6,
      "NEET_female_rural_15_19_year": 45.11,
      "NEET_urban_15_19_year": 30.13,
      "NEET_male_urban_15_19_year": 21.25,
      "NEET_female_urban_15_19_year": 38.32,
      "NEET_20_24_year_overall": 48.59,
      "NEET_male_20_24_year": 17.82,
      "NEET_female_20_24_year": 73.85,
      "NEET_rural_20_24_year": 49.1,
      "NEET_male_rural_20_24_year": 17.75,
      "NEET_female_rural_20_24_year": 74.82,
      "NEET_urban_20_24_year": 45.83,
      "NEET_male_urban_20_24_year": 18.18,
      "NEET_female_urban_20_24_year": 68.62
    },
    "Sylhet": {
      "NEET_Overall_15_24": 36.26,
      "NEET_male_Overall_15_24": 19.7,
      "NEET_female_Overall_15_24": 51.63,
      "NEET_rural_Overall_15_24": 38.14,
      "NEET_male_rural_Overall_15_24": 21.67,
      "NEET_female_rural_Overall_15_24": 53,
      "NEET_urban_Overall_15_24": 31.08,
      "NEET_male_urban_Overall_15_24": 14.55,
      "NEET_female_urban_Overall_15_24": 47.67,
      "NEET_15_19_year_overall": 29.04,
      "NEET_male_15_19_year": 21.19,
      "NEET_female_15_19_year": 36.77,
      "NEET_rural_15_19_year": 30.48,
      "NEET_male_rural_15_19_year": 23.11,
      "NEET_female_rural_15_19_year": 37.56,
      "NEET_urban_15_19_year": 24.74,
      "NEET_male_urban_15_19_year": 15.72,
      "NEET_female_urban_15_19_year": 34.3,
      "NEET_20_24_year_overall": 44.52,
      "NEET_male_20_24_year": 17.89,
      "NEET_female_20_24_year": 67.61,
      "NEET_rural_20_24_year": 47.27,
      "NEET_male_rural_20_24_year": 19.82,
      "NEET_female_rural_20_24_year": 70.24,
      "NEET_urban_20_24_year": 37.53,
      "NEET_male_urban_20_24_year": 13.3,
      "NEET_female_urban_20_24_year": 60.51
    },
    "Tangail": {
      "NEET_Overall_15_24": 35.9,
      "NEET_male_Overall_15_24": 14.37,
      "NEET_female_Overall_15_24": 54.39,
      "NEET_rural_Overall_15_24": 37.52,
      "NEET_male_rural_Overall_15_24": 15.12,
      "NEET_female_rural_Overall_15_24": 56.63,
      "NEET_urban_Overall_15_24": 30.76,
      "NEET_male_urban_Overall_15_24": 12.01,
      "NEET_female_urban_Overall_15_24": 47.14,
      "NEET_15_19_year_overall": 26.25,
      "NEET_male_15_19_year": 13.39,
      "NEET_female_15_19_year": 38.69,
      "NEET_rural_15_19_year": 27.57,
      "NEET_male_rural_15_19_year": 14.13,
      "NEET_female_rural_15_19_year": 40.56,
      "NEET_urban_15_19_year": 22.01,
      "NEET_male_urban_15_19_year": 11.03,
      "NEET_female_urban_15_19_year": 32.69,
      "NEET_20_24_year_overall": 47.38,
      "NEET_male_20_24_year": 15.72,
      "NEET_female_20_24_year": 70.91,
      "NEET_rural_20_24_year": 49.36,
      "NEET_male_rural_20_24_year": 16.49,
      "NEET_female_rural_20_24_year": 73.54,
      "NEET_urban_20_24_year": 41.08,
      "NEET_male_urban_20_24_year": 13.32,
      "NEET_female_urban_20_24_year": 62.42
    },
    "Thakurgaon": {
      "NEET_Overall_15_24": 34.26,
      "NEET_male_Overall_15_24": 11.79,
      "NEET_female_Overall_15_24": 54.85,
      "NEET_rural_Overall_15_24": 35.67,
      "NEET_male_rural_Overall_15_24": 12.29,
      "NEET_female_rural_Overall_15_24": 57.01,
      "NEET_urban_Overall_15_24": 28.49,
      "NEET_male_urban_Overall_15_24": 9.74,
      "NEET_female_urban_Overall_15_24": 45.9,
      "NEET_15_19_year_overall": 23.68,
      "NEET_male_15_19_year": 11.15,
      "NEET_female_15_19_year": 36.25,
      "NEET_rural_15_19_year": 24.77,
      "NEET_male_rural_15_19_year": 11.72,
      "NEET_female_rural_15_19_year": 37.78,
      "NEET_urban_15_19_year": 19.22,
      "NEET_male_urban_15_19_year": 8.87,
      "NEET_female_urban_15_19_year": 29.9,
      "NEET_20_24_year_overall": 46.63,
      "NEET_male_20_24_year": 12.62,
      "NEET_female_20_24_year": 74.65,
      "NEET_rural_20_24_year": 48.38,
      "NEET_male_rural_20_24_year": 13.03,
      "NEET_female_rural_20_24_year": 77.52,
      "NEET_urban_20_24_year": 39.41,
      "NEET_male_urban_20_24_year": 10.9,
      "NEET_female_urban_20_24_year": 62.79
    }
  }
}